{"boards": [
{ "board": "espressif:esp32:esp32p4",
                "target": "esp32p4",
                "sketches": [
{"name": "ArduinoOTA/examples/BasicOTA",
                    "sizes": [{
                            "flash_bytes": 730329,
                            "flash_percentage": 55,
                            "ram_bytes": 33124,
                            "ram_percentage": 10
                            }]
                    },
{"name": "AsyncUDP/examples/AsyncUDPClient",
                    "sizes": [{
                            "flash_bytes": 652129,
                            "flash_percentage": 49,
                            "ram_bytes": 27248,
                            "ram_percentage": 8
                            }]
                    },
{"name": "AsyncUDP/examples/AsyncUDPMulticastServer",
                    "sizes": [{
                            "flash_bytes": 652421,
                            "flash_percentage": 49,
                            "ram_bytes": 27248,
                            "ram_percentage": 8
                            }]
                    },
{"name": "AsyncUDP/examples/AsyncUDPServer",
                    "sizes": [{
                            "flash_bytes": 652059,
                            "flash_percentage": 49,
                            "ram_bytes": 27248,
                            "ram_percentage": 8
                            }]
                    },
{"name": "DNSServer/examples/CaptivePortal",
                    "sizes": [{
                            "flash_bytes": 709679,
                            "flash_percentage": 54,
                            "ram_bytes": 28884,
                            "ram_percentage": 8
                            }]
                    },
{"name": "EEPROM/examples/eeprom_class",
                    "sizes": [{
                            "flash_bytes": 333179,
                            "flash_percentage": 25,
                            "ram_bytes": 21600,
                            "ram_percentage": 6
                            }]
                    },
{"name": "EEPROM/examples/eeprom_extra",
                    "sizes": [{
                            "flash_bytes": 336225,
                            "flash_percentage": 25,
                            "ram_bytes": 21552,
                            "ram_percentage": 6
                            }]
                    },
{"name": "EEPROM/examples/eeprom_write",
                    "sizes": [{
                            "flash_bytes": 331733,
                            "flash_percentage": 25,
                            "ram_bytes": 21560,
                            "ram_percentage": 6
                            }]
                    },
{"name": "ESP32/examples/AnalogOut/LEDCFade",
                    "sizes": [{
                            "flash_bytes": 335551,
                            "flash_percentage": 25,
                            "ram_bytes": 21680,
                            "ram_percentage": 6
                            }]
                    },
{"name": "ESP32/examples/AnalogOut/LEDCGammaFade",
                    "sizes": [{
                            "flash_bytes": 343889,
                            "flash_percentage": 26,
                            "ram_bytes": 21696,
                            "ram_percentage": 6
                            }]
                    },
{"name": "ESP32/examples/AnalogOut/LEDCSingleChannel",
                    "sizes": [{
                            "flash_bytes": 313383,
                            "flash_percentage": 23,
                            "ram_bytes": 21676,
                            "ram_percentage": 6
                            }]
                    },
{"name": "ESP32/examples/AnalogOut/LEDCSoftwareFade",
                    "sizes": [{
                            "flash_bytes": 313433,
                            "flash_percentage": 23,
                            "ram_bytes": 21676,
                            "ram_percentage": 6
                            }]
                    }
]
},
{ "board": "espressif:esp32:esp32s3",
                "target": "esp32s3",
                "sketches": [
{"name": "ArduinoOTA/examples/BasicOTA",
                    "sizes": [{
                            "flash_bytes": 933258,
                            "flash_percentage": 71,
                            "ram_bytes": 50412,
                            "ram_percentage": 15
                            }]
                    },
{"name": "AsyncUDP/examples/AsyncUDPClient",
                    "sizes": [{
                            "flash_bytes": 856978,
                            "flash_percentage": 65,
                            "ram_bytes": 44260,
                            "ram_percentage": 13
                            }]
                    },
{"name": "AsyncUDP/examples/AsyncUDPMulticastServer",
                    "sizes": [{
                            "flash_bytes": 857294,
                            "flash_percentage": 65,
                            "ram_bytes": 44260,
                            "ram_percentage": 13
                            }]
                    },
{"name": "AsyncUDP/examples/AsyncUDPServer",
                    "sizes": [{
                            "flash_bytes": 856946,
                            "flash_percentage": 65,
                            "ram_bytes": 44260,
                            "ram_percentage": 13
                            }]
                    },
{"name": "BLE/examples/BLE5_extended_scan",
                    "sizes": [{
                            "flash_bytes": 884926,
                            "flash_percentage": 28,
                            "ram_bytes": 47356,
                            "ram_percentage": 14
                            }]
                    },
{"name": "BLE/examples/BLE5_multi_advertising",
                    "sizes": [{
                            "flash_bytes": 885770,
                            "flash_percentage": 28,
                            "ram_bytes": 47732,
                            "ram_percentage": 14
                            }]
                    },
{"name": "BLE/examples/BLE5_periodic_advertising",
                    "sizes": [{
                            "flash_bytes": 885530,
                            "flash_percentage": 28,
                            "ram_bytes": 47476,
                            "ram_percentage": 14
                            }]
                    },
{"name": "BLE/examples/BLE5_periodic_sync",
                    "sizes": [{
                            "flash_bytes": 885474,
                            "flash_percentage": 28,
                            "ram_bytes": 47372,
                            "ram_percentage": 14
                            }]
                    },
{"name": "BLE/examples/Beacon_Scanner",
                    "sizes": [{
                            "flash_bytes": 891030,
                            "flash_percentage": 28,
                            "ram_bytes": 47356,
                            "ram_percentage": 14
                            }]
                    },
{"name": "BLE/examples/Client",
                    "sizes": [{
                            "flash_bytes": 903134,
                            "flash_percentage": 28,
                            "ram_bytes": 47404,
                            "ram_percentage": 14
                            }]
                    },
{"name": "BLE/examples/EddystoneTLM_Beacon",
                    "sizes": [{
                            "flash_bytes": 895870,
                            "flash_percentage": 28,
                            "ram_bytes": 47452,
                            "ram_percentage": 14
                            }]
                    },
{"name": "BLE/examples/EddystoneURL_Beacon",
                    "sizes": [{
                            "flash_bytes": 896142,
                            "flash_percentage": 28,
                            "ram_bytes": 47540,
                            "ram_percentage": 14
                            }]
                    },
{"name": "BLE/examples/Notify",
                    "sizes": [{
                            "flash_bytes": 897270,
                            "flash_percentage": 28,
                            "ram_bytes": 47372,
                            "ram_percentage": 14
                            }]
                    },
{"name": "BLE/examples/Scan",
                    "sizes": [{
                            "flash_bytes": 887194,
                            "flash_percentage": 28,
                            "ram_bytes": 47356,
                            "ram_percentage": 14
                            }]
                    },
{"name": "BLE/examples/Server",
                    "sizes": [{
                            "flash_bytes": 893090,
                            "flash_percentage": 28,
                            "ram_bytes": 47356,
                            "ram_percentage": 14
                            }]
                    },
{"name": "BLE/examples/Server_multiconnect",
                    "sizes": [{
                            "flash_bytes": 896674,
                            "flash_percentage": 28,
                            "ram_bytes": 47372,
                            "ram_percentage": 14
                            }]
                    }
]
},
{ "board": "espressif:esp32:esp32s2",
                "target": "esp32s2",
                "sketches": [
{"name": "ArduinoOTA/examples/BasicOTA",
                    "sizes": [{
                            "flash_bytes": 895533,
                            "flash_percentage": 68,
                            "ram_bytes": 44820,
                            "ram_percentage": 13
                            }]
                    },
{"name": "AsyncUDP/examples/AsyncUDPClient",
                    "sizes": [{
                            "flash_bytes": 825937,
                            "flash_percentage": 63,
                            "ram_bytes": 38736,
                            "ram_percentage": 11
                            }]
                    },
{"name": "AsyncUDP/examples/AsyncUDPMulticastServer",
                    "sizes": [{
                            "flash_bytes": 826269,
                            "flash_percentage": 63,
                            "ram_bytes": 38736,
                            "ram_percentage": 11
                            }]
                    },
{"name": "AsyncUDP/examples/AsyncUDPServer",
                    "sizes": [{
                            "flash_bytes": 825905,
                            "flash_percentage": 63,
                            "ram_bytes": 38736,
                            "ram_percentage": 11
                            }]
                    },
{"name": "DNSServer/examples/CaptivePortal",
                    "sizes": [{
                            "flash_bytes": 873493,
                            "flash_percentage": 66,
                            "ram_bytes": 40432,
                            "ram_percentage": 12
                            }]
                    },
{"name": "EEPROM/examples/eeprom_class",
                    "sizes": [{
                            "flash_bytes": 277669,
                            "flash_percentage": 21,
                            "ram_bytes": 15268,
                            "ram_percentage": 4
                            }]
                    },
{"name": "EEPROM/examples/eeprom_extra",
                    "sizes": [{
                            "flash_bytes": 279781,
                            "flash_percentage": 21,
                            "ram_bytes": 15212,
                            "ram_percentage": 4
                            }]
                    },
{"name": "EEPROM/examples/eeprom_write",
                    "sizes": [{
                            "flash_bytes": 276133,
                            "flash_percentage": 21,
                            "ram_bytes": 15212,
                            "ram_percentage": 4
                            }]
                    },
{"name": "ESP32/examples/AnalogOut/LEDCFade",
                    "sizes": [{
                            "flash_bytes": 279673,
                            "flash_percentage": 21,
                            "ram_bytes": 15344,
                            "ram_percentage": 4
                            }]
                    },
{"name": "ESP32/examples/AnalogOut/LEDCSingleChannel",
                    "sizes": [{
                            "flash_bytes": 262429,
                            "flash_percentage": 20,
                            "ram_bytes": 15328,
                            "ram_percentage": 4
                            }]
                    },
{"name": "ESP32/examples/AnalogOut/LEDCSoftwareFade",
                    "sizes": [{
                            "flash_bytes": 262501,
                            "flash_percentage": 20,
                            "ram_bytes": 15328,
                            "ram_percentage": 4
                            }]
                    },
{"name": "ESP32/examples/AnalogOut/SigmaDelta",
                    "sizes": [{
                            "flash_bytes": 258129,
                            "flash_percentage": 19,
                            "ram_bytes": 15180,
                            "ram_percentage": 4
                            }]
                    },
{"name": "ESP32/examples/AnalogOut/ledcFrequency",
                    "sizes": [{
                            "flash_bytes": 264417,
                            "flash_percentage": 20,
                            "ram_bytes": 15320,
                            "ram_percentage": 4
                            }]
                    },
{"name": "ESP32/examples/AnalogOut/ledcWrite_RGB",
                    "sizes": [{
                            "flash_bytes": 276301,
                            "flash_percentage": 21,
                            "ram_bytes": 15352,
                            "ram_percentage": 4
                            }]
                    },
{"name": "ESP32/examples/AnalogRead",
                    "sizes": [{
                            "flash_bytes": 280089,
                            "flash_percentage": 21,
                            "ram_bytes": 15348,
                            "ram_percentage": 4
                            }]
                    }
]
},
{ "board": "espressif:esp32:esp32c3",
                "target": "esp32c3",
                "sketches": [
{"name": "ArduinoOTA/examples/BasicOTA",
                    "sizes": [{
                            "flash_bytes": 1007026,
                            "flash_percentage": 76,
                            "ram_bytes": 41768,
                            "ram_percentage": 12
                            }]
                    },
{"name": "AsyncUDP/examples/AsyncUDPClient",
                    "sizes": [{
                            "flash_bytes": 923628,
                            "flash_percentage": 70,
                            "ram_bytes": 35016,
                            "ram_percentage": 10
                            }]
                    },
{"name": "AsyncUDP/examples/AsyncUDPMulticastServer",
                    "sizes": [{
                            "flash_bytes": 924042,
                            "flash_percentage": 70,
                            "ram_bytes": 35016,
                            "ram_percentage": 10
                            }]
                    },
{"name": "AsyncUDP/examples/AsyncUDPServer",
                    "sizes": [{
                            "flash_bytes": 923560,
                            "flash_percentage": 70,
                            "ram_bytes": 35016,
                            "ram_percentage": 10
                            }]
                    },
{"name": "BLE/examples/BLE5_extended_scan",
                    "sizes": [{
                            "flash_bytes": 952202,
                            "flash_percentage": 30,
                            "ram_bytes": 37552,
                            "ram_percentage": 11
                            }]
                    },
{"name": "BLE/examples/BLE5_multi_advertising",
                    "sizes": [{
                            "flash_bytes": 953334,
                            "flash_percentage": 30,
                            "ram_bytes": 37912,
                            "ram_percentage": 11
                            }]
                    },
{"name": "BLE/examples/BLE5_periodic_advertising",
                    "sizes": [{
                            "flash_bytes": 953132,
                            "flash_percentage": 30,
                            "ram_bytes": 37648,
                            "ram_percentage": 11
                            }]
                    },
{"name": "BLE/examples/BLE5_periodic_sync",
                    "sizes": [{
                            "flash_bytes": 952702,
                            "flash_percentage": 30,
                            "ram_bytes": 37560,
                            "ram_percentage": 11
                            }]
                    },
{"name": "BLE/examples/Beacon_Scanner",
                    "sizes": [{
                            "flash_bytes": 960414,
                            "flash_percentage": 30,
                            "ram_bytes": 37552,
                            "ram_percentage": 11
                            }]
                    },
{"name": "BLE/examples/Client",
                    "sizes": [{
                            "flash_bytes": 973410,
                            "flash_percentage": 30,
                            "ram_bytes": 37584,
                            "ram_percentage": 11
                            }]
                    },
{"name": "BLE/examples/EddystoneTLM_Beacon",
                    "sizes": [{
                            "flash_bytes": 962634,
                            "flash_percentage": 30,
                            "ram_bytes": 37696,
                            "ram_percentage": 11
                            }]
                    },
{"name": "BLE/examples/EddystoneURL_Beacon",
                    "sizes": [{
                            "flash_bytes": 963178,
                            "flash_percentage": 30,
                            "ram_bytes": 37776,
                            "ram_percentage": 11
                            }]
                    },
{"name": "BLE/examples/Notify",
                    "sizes": [{
                            "flash_bytes": 967864,
                            "flash_percentage": 30,
                            "ram_bytes": 37560,
                            "ram_percentage": 11
                            }]
                    },
{"name": "BLE/examples/Scan",
                    "sizes": [{
                            "flash_bytes": 955126,
                            "flash_percentage": 30,
                            "ram_bytes": 37552,
                            "ram_percentage": 11
                            }]
                    }
]
},
{ "board": "espressif:esp32:esp32c6",
                "target": "esp32c6",
                "sketches": [
{"name": "ArduinoOTA/examples/BasicOTA",
                    "sizes": [{
                            "flash_bytes": 1015225,
                            "flash_percentage": 77,
                            "ram_bytes": 47844,
                            "ram_percentage": 14
                            }]
                    },
{"name": "AsyncUDP/examples/AsyncUDPClient",
                    "sizes": [{
                            "flash_bytes": 931675,
                            "flash_percentage": 71,
                            "ram_bytes": 41092,
                            "ram_percentage": 12
                            }]
                    },
{"name": "AsyncUDP/examples/AsyncUDPMulticastServer",
                    "sizes": [{
                            "flash_bytes": 932091,
                            "flash_percentage": 71,
                            "ram_bytes": 41092,
                            "ram_percentage": 12
                            }]
                    },
{"name": "AsyncUDP/examples/AsyncUDPServer",
                    "sizes": [{
                            "flash_bytes": 931609,
                            "flash_percentage": 71,
                            "ram_bytes": 41092,
                            "ram_percentage": 12
                            }]
                    },
{"name": "BLE/examples/BLE5_extended_scan",
                    "sizes": [{
                            "flash_bytes": 1043361,
                            "flash_percentage": 33,
                            "ram_bytes": 38336,
                            "ram_percentage": 11
                            }]
                    },
{"name": "BLE/examples/BLE5_multi_advertising",
                    "sizes": [{
                            "flash_bytes": 1044531,
                            "flash_percentage": 33,
                            "ram_bytes": 38720,
                            "ram_percentage": 11
                            }]
                    },
{"name": "BLE/examples/BLE5_periodic_advertising",
                    "sizes": [{
                            "flash_bytes": 1044327,
                            "flash_percentage": 33,
                            "ram_bytes": 38456,
                            "ram_percentage": 11
                            }]
                    },
{"name": "BLE/examples/BLE5_periodic_sync",
                    "sizes": [{
                            "flash_bytes": 1043857,
                            "flash_percentage": 33,
                            "ram_bytes": 38352,
                            "ram_percentage": 11
                            }]
                    },
{"name": "BLE/examples/Beacon_Scanner",
                    "sizes": [{
                            "flash_bytes": 1051605,
                            "flash_percentage": 33,
                            "ram_bytes": 38336,
                            "ram_percentage": 11
                            }]
                    },
{"name": "BLE/examples/Client",
                    "sizes": [{
                            "flash_bytes": 1064581,
                            "flash_percentage": 33,
                            "ram_bytes": 38384,
                            "ram_percentage": 11
                            }]
                    },
{"name": "BLE/examples/EddystoneTLM_Beacon",
                    "sizes": [{
                            "flash_bytes": 1056433,
                            "flash_percentage": 33,
                            "ram_bytes": 38576,
                            "ram_percentage": 11
                            }]
                    },
{"name": "BLE/examples/EddystoneURL_Beacon",
                    "sizes": [{
                            "flash_bytes": 1056977,
                            "flash_percentage": 33,
                            "ram_bytes": 38656,
                            "ram_percentage": 11
                            }]
                    },
{"name": "BLE/examples/Notify",
                    "sizes": [{
                            "flash_bytes": 1059015,
                            "flash_percentage": 33,
                            "ram_bytes": 38344,
                            "ram_percentage": 11
                            }]
                    },
{"name": "BLE/examples/Scan",
                    "sizes": [{
                            "flash_bytes": 1046293,
                            "flash_percentage": 33,
                            "ram_bytes": 38336,
                            "ram_percentage": 11
                            }]
                    },
{"name": "BLE/examples/Server",
                    "sizes": [{
                            "flash_bytes": 1053707,
                            "flash_percentage": 33,
                            "ram_bytes": 38328,
                            "ram_percentage": 11
                            }]
                    },
{"name": "BLE/examples/Server_multiconnect",
                    "sizes": [{
                            "flash_bytes": 1058357,
                            "flash_percentage": 33,
                            "ram_bytes": 38344,
                            "ram_percentage": 11
                            }]
                    }
]
},
{ "board": "espressif:esp32:esp32h2",
                "target": "esp32h2",
                "sketches": [
{"name": "BLE/examples/BLE5_extended_scan",
                    "sizes": [{
                            "flash_bytes": 1100557,
                            "flash_percentage": 34,
                            "ram_bytes": 37352,
                            "ram_percentage": 11
                            }]
                    },
{"name": "BLE/examples/BLE5_multi_advertising",
                    "sizes": [{
                            "flash_bytes": 1101707,
                            "flash_percentage": 35,
                            "ram_bytes": 37744,
                            "ram_percentage": 11
                            }]
                    },
{"name": "BLE/examples/BLE5_periodic_advertising",
                    "sizes": [{
                            "flash_bytes": 1101503,
                            "flash_percentage": 35,
                            "ram_bytes": 37480,
                            "ram_percentage": 11
                            }]
                    },
{"name": "BLE/examples/BLE5_periodic_sync",
                    "sizes": [{
                            "flash_bytes": 1101073,
                            "flash_percentage": 35,
                            "ram_bytes": 37376,
                            "ram_percentage": 11
                            }]
                    },
{"name": "BLE/examples/Beacon_Scanner",
                    "sizes": [{
                            "flash_bytes": 1108777,
                            "flash_percentage": 35,
                            "ram_bytes": 37352,
                            "ram_percentage": 11
                            }]
                    },
{"name": "BLE/examples/Client",
                    "sizes": [{
                            "flash_bytes": 1121781,
                            "flash_percentage": 35,
                            "ram_bytes": 37400,
                            "ram_percentage": 11
                            }]
                    },
{"name": "BLE/examples/EddystoneTLM_Beacon",
                    "sizes": [{
                            "flash_bytes": 1112765,
                            "flash_percentage": 35,
                            "ram_bytes": 37560,
                            "ram_percentage": 11
                            }]
                    },
{"name": "BLE/examples/EddystoneURL_Beacon",
                    "sizes": [{
                            "flash_bytes": 1113317,
                            "flash_percentage": 35,
                            "ram_bytes": 37640,
                            "ram_percentage": 11
                            }]
                    },
{"name": "BLE/examples/Notify",
                    "sizes": [{
                            "flash_bytes": 1116235,
                            "flash_percentage": 35,
                            "ram_bytes": 37376,
                            "ram_percentage": 11
                            }]
                    }
]
},
{ "board": "espressif:esp32:esp32",
                "target": "esp32",
                "sketches": [
{"name": "ArduinoOTA/examples/BasicOTA",
                    "sizes": [{
                            "flash_bytes": 956922,
                            "flash_percentage": 73,
                            "ram_bytes": 50568,
                            "ram_percentage": 15
                            }]
                    },
{"name": "AsyncUDP/examples/AsyncUDPClient",
                    "sizes": [{
                            "flash_bytes": 900510,
                            "flash_percentage": 68,
                            "ram_bytes": 44728,
                            "ram_percentage": 13
                            }]
                    },
{"name": "AsyncUDP/examples/AsyncUDPMulticastServer",
                    "sizes": [{
                            "flash_bytes": 900850,
                            "flash_percentage": 68,
                            "ram_bytes": 44728,
                            "ram_percentage": 13
                            }]
                    },
{"name": "AsyncUDP/examples/AsyncUDPServer",
                    "sizes": [{
                            "flash_bytes": 900458,
                            "flash_percentage": 68,
                            "ram_bytes": 44728,
                            "ram_percentage": 13
                            }]
                    },
{"name": "BLE/examples/Beacon_Scanner",
                    "sizes": [{
                            "flash_bytes": 1099666,
                            "flash_percentage": 34,
                            "ram_bytes": 40192,
                            "ram_percentage": 12
                            }]
                    },
{"name": "BLE/examples/Client",
                    "sizes": [{
                            "flash_bytes": 1111678,
                            "flash_percentage": 35,
                            "ram_bytes": 40248,
                            "ram_percentage": 12
                            }]
                    },
{"name": "BLE/examples/EddystoneTLM_Beacon",
                    "sizes": [{
                            "flash_bytes": 1102590,
                            "flash_percentage": 35,
                            "ram_bytes": 40340,
                            "ram_percentage": 12
                            }]
                    },
{"name": "BLE/examples/EddystoneURL_Beacon",
                    "sizes": [{
                            "flash_bytes": 1102582,
                            "flash_percentage": 35,
                            "ram_bytes": 40320,
                            "ram_percentage": 12
                            }]
                    },
{"name": "BLE/examples/Notify",
                    "sizes": [{
                            "flash_bytes": 1105850,
                            "flash_percentage": 35,
                            "ram_bytes": 40216,
                            "ram_percentage": 12
                            }]
                    },
{"name": "BLE/examples/Scan",
                    "sizes": [{
                            "flash_bytes": 1095626,
                            "flash_percentage": 34,
                            "ram_bytes": 40192,
                            "ram_percentage": 12
                            }]
                    },
{"name": "BLE/examples/Server",
                    "sizes": [{
                            "flash_bytes": 1101558,
                            "flash_percentage": 35,
                            "ram_bytes": 40192,
                            "ram_percentage": 12
                            }]
                    },
{"name": "BLE/examples/Server_multiconnect",
                    "sizes": [{
                            "flash_bytes": 1105258,
                            "flash_percentage": 35,
                            "ram_bytes": 40208,
                            "ram_percentage": 12
                            }]
                    },
{"name": "BLE/examples/UART",
                    "sizes": [{
                            "flash_bytes": 1105622,
                            "flash_percentage": 35,
                            "ram_bytes": 40208,
                            "ram_percentage": 12
                            }]
                    },
{"name": "BLE/examples/Write",
                    "sizes": [{
                            "flash_bytes": 1102002,
                            "flash_percentage": 35,
                            "ram_bytes": 40200,
                            "ram_percentage": 12
                            }]
                    },
{"name": "BLE/examples/iBeacon",
                    "sizes": [{
                            "flash_bytes": 1107774,
                            "flash_percentage": 35,
                            "ram_bytes": 40208,
                            "ram_percentage": 12
                            }]
                    }
]
}
]}
